iker/common/__init__.py
iker/common/utils/__init__.py
iker/common/utils/argutils.py
iker/common/utils/config.py
iker/common/utils/csv.py
iker/common/utils/dbutils.py
iker/common/utils/dockerutils.py
iker/common/utils/dtutils.py
iker/common/utils/funcutils.py
iker/common/utils/jsonutils.py
iker/common/utils/logger.py
iker/common/utils/numutils.py
iker/common/utils/randutils.py
iker/common/utils/retry.py
iker/common/utils/sequtils.py
iker/common/utils/shutils.py
iker/common/utils/span.py
iker/common/utils/strutils.py
iker/common/utils/testutils.py
iker/common/utils/typeutils.py
iker_python_common-1.0.62.dist-info/METADATA
iker_python_common-1.0.62.dist-info/WHEEL
iker_python_common-1.0.62.dist-info/top_level.txt
iker_python_common-1.0.62.dist-info/RECORD
