Metadata-Version: 2.4
Name: iker-python-common
Version: 1.0.62
Classifier: Programming Language :: Python :: 3
Classifier: Programming Language :: Python :: 3.12
Classifier: Programming Language :: Python :: 3.13
Classifier: Programming Language :: Python :: 3.14
Requires-Python: <3.15,>=3.12
Requires-Dist: asyncpg>=0.30
Requires-Dist: docker>=7.1
Requires-Dist: numpy>=2.3
Requires-Dist: psycopg>=3.2
Requires-Dist: pymysql>=1.1
Requires-Dist: sqlalchemy>=2.0
Provides-Extra: all
Requires-Dist: iker-python-common; extra == "all"
Provides-Extra: test
Requires-Dist: ddt>=1.7; extra == "test"
Requires-Dist: pytest-asyncio>=1.2; extra == "test"
Requires-Dist: pytest-cov>=5.0; extra == "test"
Requires-Dist: pytest-mysql>=3.0; extra == "test"
Requires-Dist: pytest-order>=1.3; extra == "test"
Requires-Dist: pytest-postgresql>=6.1; extra == "test"
Requires-Dist: pytest>=8.3; extra == "test"
